pool_log/__init__.py
pool_log/db.py
pool_log/log.py
pool_log/pool.py
pool_log/schema.sql
pool_log/static/style.css
pool_log/static/timezone.js
pool_log/templates/base.html
pool_log/templates/log/create.html
pool_log/templates/log/index.html
pool_log/templates/pools/create.html
pool_log/templates/pools/select.html
pool_log_zach_13_wells-0.1.4.dist-info/METADATA
pool_log_zach_13_wells-0.1.4.dist-info/WHEEL
pool_log_zach_13_wells-0.1.4.dist-info/licenses/LICENSE
pool_log_zach_13_wells-0.1.4.dist-info/RECORD
