Metadata-Version: 2.1
Name: pool_log_zach_13_wells
Version: 0.1.4
Summary: A Flask application for logging pool water quality
Project-URL: Homepage, https://github.com/adinfinitum225/pool-log
Author-email: Zachary Wells <zach.13.wells@gmail.com>
License-File: LICENSE
Classifier: License :: OSI Approved :: MIT License
Classifier: Operating System :: OS Independent
Classifier: Programming Language :: Python :: 3
